{
  "dct_title_s": "Mappe-monde, ou, Description du globe terrestre. : ou l'on trouve en general le rapportque toutes ses parties ont avec les cieux, entr'elles, et avec l'histoire",
  "dct_description_sm": [
    "Scale not given; 2 maps on 1 sheet: color; each 30 cm in diameter, on sheet 43 x 60 cm World maps--Early works to 1800"
  ],
  "dct_language_sm": [
    "eng"
  ],
  "dct_creator_sm": [
    "Moullart-Sanson"
  ],
  "schema_provider_s": "Pennsylvania State University",
  "gbl_resourceClass_sm": [
    "Maps"
  ],
  "gbl_resourceType_sm": [
    "World maps"
  ],
  "dct_temporal_sm": [
    "1800?"
  ],
  "gbl_indexYear_im": [
    "1800"
  ],
  "gbl_dateRange_drsim": [
    "[1800 TO 1800]"
  ],
  "dct_spatial_sm": [
    "World"
  ],
  "locn_geometry": "POLYGON((-179.99 89.99, 179.99 89.99, 179.99 -89.99, -179.99 -89.99, -179.99 89.99))",
  "dcat_bbox": "ENVELOPE(-179.99,179.99,89.99,-89.99)",
  "dcat_centroid": "0.0,0.0",
  "pcdm_memberOf_sm": [
    "64bd8c4c-8e60-4956-b43d-bdc3f93db488"
  ],
  "dct_isPartOf_sm": [
    "08d-01"
  ],
  "dct_accessRights_s": "Public",
  "dct_format_s": "JPEG",
  "dct_references_s": "{\"http://schema.org/url\":\"https://digital.libraries.psu.edu/digital/collection/maps1/id/26371\",\"http://iiif.io/api/presentation#manifest\":\"https://digital.libraries.psu.edu/iiif/info/maps1/26371/manifest.json\"}",
  "id": "1a962534-06e5-4c1f-97c1-5b258a0f89f3",
  "dct_identifier_sm": [
    "1a962534-06e5-4c1f-97c1-5b258a0f89f3"
  ],
  "gbl_mdVersion_s": "Aardvark"
}