{
  "dct_title_s": "Natrona, Pennsylvania, 1929",
  "dct_description_sm": [
    "Natrona, Allegheny County, Pennsylvania, October 1929. 1 map on 18 sheets : color ; sheets 65 x 54 cm.  Scale approximately 1:600. 50 ft. to an in. unless otherwise noted on individual sheets."
  ],
  "dct_language_sm": [
    "eng"
  ],
  "dct_creator_sm": [
    "Sanborn Map Company"
  ],
  "dct_publisher_sm": [
    "Sanborn Map Company"
  ],
  "schema_provider_s": "Pennsylvania State University",
  "gbl_resourceClass_sm": [
    "Maps"
  ],
  "gbl_resourceType_sm": [
    "Fire insurance maps"
  ],
  "dcat_keyword_sm": [
    "Fire risk assessment",
    "Real property",
    "Sanborn Fire Insurance Maps"
  ],
  "dct_temporal_sm": [
    "1929"
  ],
  "gbl_indexYear_im": [
    "1929"
  ],
  "gbl_dateRange_drsim": [
    "[1929 TO 1929]"
  ],
  "dct_spatial_sm": [
    "Pennsylvania--Natrona",
    "Pennsylvania--Allegheny County",
    "Pennsylvania"
  ],
  "locn_geometry": "POLYGON((-79.735 40.620, -79.717 40.620, -79.717 40.604, -79.735 40.604, -79.735 40.620))",
  "dcat_bbox": "ENVELOPE(-79.735,-79.717,40.620,40.604)",
  "dcat_centroid": "40.611999999999995,-79.726",
  "dct_relation_sm": [
    "8888-002"
  ],
  "pcdm_memberOf_sm": [
    "64bd8c4c-8e60-4956-b43d-bdc3f93db488",
    "b35f927e-9051-4d7f-9ca3-ad5b19024e0b"
  ],
  "dct_isPartOf_sm": [
    "08d-02"
  ],
  "dct_accessRights_s": "Public",
  "dct_format_s": "JPEG",
  "dct_references_s": "{\"http://schema.org/url\":\"https://digital.libraries.psu.edu/digital/collection/maps1/id/27891\",\"http://iiif.io/api/presentation#manifest\":\"https://digital.libraries.psu.edu/iiif/info/maps1/27891/manifest.json\"}",
  "id": "22e28e51-c02a-428a-ac2e-9affd7ee8c44",
  "dct_identifier_sm": [
    "22e28e51-c02a-428a-ac2e-9affd7ee8c44"
  ],
  "gbl_mdVersion_s": "Aardvark"
}