{
  "dct_title_s": "Rochester, Pennsylvania, 1892",
  "dct_description_sm": [
    "Rochester, Beaver Co., Pa., Jan. 1892. 1 map on 3 sheets : col. ; sheets 65 x 54 cm.  Scale approximately 1:600. 50 ft. to an in."
  ],
  "dct_language_sm": [
    "eng"
  ],
  "dct_creator_sm": [
    "Sanborn Map Company"
  ],
  "dct_publisher_sm": [
    "Sanborn Map Company"
  ],
  "schema_provider_s": "Pennsylvania State University",
  "gbl_resourceClass_sm": [
    "Maps"
  ],
  "gbl_resourceType_sm": [
    "Fire insurance maps"
  ],
  "dcat_keyword_sm": [
    "Fire risk assessment",
    "Real property",
    "Sanborn Fire Insurance Maps"
  ],
  "dct_temporal_sm": [
    "1892"
  ],
  "gbl_indexYear_im": [
    "1892"
  ],
  "gbl_dateRange_drsim": [
    "[1892 TO 1892]"
  ],
  "dct_spatial_sm": [
    "Pennsylvania--Rochester",
    "Pennsylvania--Beaver County",
    "Pennsylvania"
  ],
  "locn_geometry": "POLYGON((-80.294 40.710, -80.275 40.710, -80.275 40.696, -80.294 40.696, -80.294 40.710))",
  "dcat_bbox": "ENVELOPE(-80.294,-80.275,40.710,40.696)",
  "dcat_centroid": "40.703,-80.28450000000001",
  "dct_relation_sm": [
    "8888-002"
  ],
  "pcdm_memberOf_sm": [
    "64bd8c4c-8e60-4956-b43d-bdc3f93db488",
    "b35f927e-9051-4d7f-9ca3-ad5b19024e0b"
  ],
  "dct_isPartOf_sm": [
    "08d-02"
  ],
  "dct_accessRights_s": "Public",
  "dct_format_s": "JPEG",
  "dct_references_s": "{\"http://schema.org/url\":\"https://digital.libraries.psu.edu/digital/collection/maps1/id/20926\",\"http://iiif.io/api/presentation#manifest\":\"https://digital.libraries.psu.edu/iiif/info/maps1/20926/manifest.json\"}",
  "id": "397d1957-aa0e-4e6d-88b1-a8f5b41a9d41",
  "dct_identifier_sm": [
    "397d1957-aa0e-4e6d-88b1-a8f5b41a9d41"
  ],
  "gbl_mdVersion_s": "Aardvark"
}