{
  "dct_title_s": "Ambler, Pennsylvania, 1909",
  "dct_description_sm": [
    "Ambler, Montgomery County, Pennsylvania, Jan. 1909. 1 map on 13 sheets :  col. ;  on sheets 64 x 54 cm.; Publisher's title from sheet 1.  Oriented with north to the right with some sheets on the horizontal.  Includes indexes, sheet key map, key, and text. Scale approximately 1:600. 50 ft. to an in."
  ],
  "dct_language_sm": [
    "eng"
  ],
  "dct_creator_sm": [
    "Sanborn Map Company"
  ],
  "dct_publisher_sm": [
    "Sanborn Map Company"
  ],
  "schema_provider_s": "Pennsylvania State University",
  "gbl_resourceClass_sm": [
    "Maps"
  ],
  "gbl_resourceType_sm": [
    "Fire insurance maps"
  ],
  "dcat_keyword_sm": [
    "Fire risk assessment",
    "Real property",
    "Sanborn Fire Insurance Maps"
  ],
  "dct_temporal_sm": [
    "1909"
  ],
  "gbl_indexYear_im": [
    "1909"
  ],
  "gbl_dateRange_drsim": [
    "[1909 TO 1909]"
  ],
  "dct_spatial_sm": [
    "Pennsylvania--Ambler",
    "Pennsylvania--Montgomery County",
    "Pennsylvania"
  ],
  "locn_geometry": "POLYGON((-75.231 40.168, -75.213 40.168, -75.213 40.145, -75.231 40.145, -75.231 40.168))",
  "dcat_bbox": "ENVELOPE(-75.231,-75.213,40.168,40.145)",
  "dcat_centroid": "40.1565,-75.222",
  "dct_relation_sm": [
    "8888-002"
  ],
  "pcdm_memberOf_sm": [
    "64bd8c4c-8e60-4956-b43d-bdc3f93db488",
    "b35f927e-9051-4d7f-9ca3-ad5b19024e0b"
  ],
  "dct_isPartOf_sm": [
    "08d-02"
  ],
  "dct_accessRights_s": "Public",
  "dct_format_s": "JPEG",
  "dct_references_s": "{\"http://schema.org/url\":\"https://digital.libraries.psu.edu/digital/collection/maps1/id/2230\",\"http://iiif.io/api/presentation#manifest\":\"https://digital.libraries.psu.edu/iiif/info/maps1/2230/manifest.json\"}",
  "id": "8a0f7e0a-0baf-4fa0-9d84-85bdfb43011f",
  "dct_identifier_sm": [
    "8a0f7e0a-0baf-4fa0-9d84-85bdfb43011f"
  ],
  "gbl_mdVersion_s": "Aardvark"
}