{
  "dct_title_s": "New Gallilee sic, Pennsylvania, 1921",
  "dct_description_sm": [
    "New Gallilee [sic], Beaver County, Pennsylvania, August 1921. 1 map on 2 sheets : col. ; sheets 65 x 54 cm.  Scale approximately 1:600. 50 ft. to an in."
  ],
  "dct_language_sm": [
    "eng"
  ],
  "dct_creator_sm": [
    "Sanborn Map Company"
  ],
  "dct_publisher_sm": [
    "Sanborn Map Company"
  ],
  "schema_provider_s": "Pennsylvania State University",
  "gbl_resourceClass_sm": [
    "Maps"
  ],
  "gbl_resourceType_sm": [
    "Fire insurance maps"
  ],
  "dcat_keyword_sm": [
    "Fire risk assessment",
    "Real property",
    "Sanborn Fire Insurance Maps"
  ],
  "dct_temporal_sm": [
    "1921"
  ],
  "gbl_indexYear_im": [
    "1921"
  ],
  "gbl_dateRange_drsim": [
    "[1921 TO 1921]"
  ],
  "dct_spatial_sm": [
    "Pennsylvania--New Gallilee (sic)",
    "Pennsylvania--Beaver County",
    "Pennsylvania"
  ],
  "locn_geometry": "POLYGON((-80.411 40.843, -80.390 40.843, -80.390 40.827, -80.411 40.827, -80.411 40.843))",
  "dcat_bbox": "ENVELOPE(-80.411,-80.390,40.843,40.827)",
  "dcat_centroid": "40.835,-80.4005",
  "dct_relation_sm": [
    "8888-002"
  ],
  "pcdm_memberOf_sm": [
    "64bd8c4c-8e60-4956-b43d-bdc3f93db488",
    "b35f927e-9051-4d7f-9ca3-ad5b19024e0b"
  ],
  "dct_isPartOf_sm": [
    "08d-02"
  ],
  "dct_accessRights_s": "Public",
  "dct_format_s": "JPEG",
  "dct_references_s": "{\"http://schema.org/url\":\"https://digital.libraries.psu.edu/digital/collection/maps1/id/16478\",\"http://iiif.io/api/presentation#manifest\":\"https://digital.libraries.psu.edu/iiif/info/maps1/16478/manifest.json\"}",
  "id": "979a5a93-9d51-466e-9bf9-f6928e04152e",
  "dct_identifier_sm": [
    "979a5a93-9d51-466e-9bf9-f6928e04152e"
  ],
  "gbl_mdVersion_s": "Aardvark"
}