{
  "dct_title_s": "Bedford, Pennsylvania, 1906",
  "dct_description_sm": [
    "Bedford, Bedford Co., Pennsylvania, December 1906. 1 map on 4 sheets : col. ; sheets 64 x 54 cm. + title sheet (sheet 1) and sheet of ancillary maps (sheet 6).  Scale approximately 1:600. 50 ft. to an in."
  ],
  "dct_language_sm": [
    "eng"
  ],
  "dct_creator_sm": [
    "Sanborn Map Company"
  ],
  "dct_publisher_sm": [
    "Sanborn Map Company"
  ],
  "schema_provider_s": "Pennsylvania State University",
  "gbl_resourceClass_sm": [
    "Maps"
  ],
  "gbl_resourceType_sm": [
    "Fire insurance maps"
  ],
  "dcat_keyword_sm": [
    "Fire risk assessment",
    "Real property",
    "Sanborn Fire Insurance Maps"
  ],
  "dct_temporal_sm": [
    "1906"
  ],
  "gbl_indexYear_im": [
    "1906"
  ],
  "gbl_dateRange_drsim": [
    "[1906 TO 1906]"
  ],
  "dct_spatial_sm": [
    "Pennsylvania--Bedford",
    "Pennsylvania--Bedford County",
    "Pennsylvania"
  ],
  "locn_geometry": "POLYGON((-78.517 40.026, -78.486 40.026, -78.486 40.003, -78.517 40.003, -78.517 40.026))",
  "dcat_bbox": "ENVELOPE(-78.517,-78.486,40.026,40.003)",
  "dcat_centroid": "40.0145,-78.5015",
  "dct_relation_sm": [
    "8888-002"
  ],
  "pcdm_memberOf_sm": [
    "64bd8c4c-8e60-4956-b43d-bdc3f93db488",
    "b35f927e-9051-4d7f-9ca3-ad5b19024e0b"
  ],
  "dct_isPartOf_sm": [
    "08d-02"
  ],
  "dct_accessRights_s": "Public",
  "dct_format_s": "JPEG",
  "dct_references_s": "{\"http://schema.org/url\":\"https://digital.libraries.psu.edu/digital/collection/maps1/id/3380\",\"http://iiif.io/api/presentation#manifest\":\"https://digital.libraries.psu.edu/iiif/info/maps1/3380/manifest.json\"}",
  "id": "9fe91171-c1de-4bcc-9a59-1c70e2d3e278",
  "dct_identifier_sm": [
    "9fe91171-c1de-4bcc-9a59-1c70e2d3e278"
  ],
  "gbl_mdVersion_s": "Aardvark"
}