{
  "dct_title_s": "Sharon, Pennsylvania, 1920",
  "dct_description_sm": [
    "Insurance maps of Sharon including Farrell [and] Wheatland, Pennsylvania, June 1920. 1 map on 35 sheets : col. ; sheets 65 x 54 cm. + Index (1 leaf ; 65 x 54 cm.).  Scale approximately 1:600. 50 ft. to an in. unless otherwise noted on individual sheets."
  ],
  "dct_language_sm": [
    "eng"
  ],
  "dct_creator_sm": [
    "Sanborn Map Company"
  ],
  "dct_publisher_sm": [
    "Sanborn Map Company"
  ],
  "schema_provider_s": "Pennsylvania State University",
  "gbl_resourceClass_sm": [
    "Maps"
  ],
  "gbl_resourceType_sm": [
    "Fire insurance maps"
  ],
  "dcat_keyword_sm": [
    "Fire risk assessment",
    "Real property",
    "Sanborn Fire Insurance Maps"
  ],
  "dct_temporal_sm": [
    "1920"
  ],
  "gbl_indexYear_im": [
    "1920"
  ],
  "gbl_dateRange_drsim": [
    "[1920 TO 1920]"
  ],
  "dct_spatial_sm": [
    "Pennsylvania--Sharon",
    "Pennsylvania--Farrell",
    "Pennsylvania--Wheatland",
    "Pennsylvania"
  ],
  "locn_geometry": "POLYGON((-80.519 41.256, -80.468 41.256, -80.468 41.188, -80.519 41.188, -80.519 41.256))",
  "dcat_bbox": "ENVELOPE(-80.519,-80.468,41.256,41.188)",
  "dcat_centroid": "41.222,-80.49350000000001",
  "dct_relation_sm": [
    "8888-002"
  ],
  "pcdm_memberOf_sm": [
    "64bd8c4c-8e60-4956-b43d-bdc3f93db488",
    "b35f927e-9051-4d7f-9ca3-ad5b19024e0b"
  ],
  "dct_isPartOf_sm": [
    "08d-02"
  ],
  "dct_accessRights_s": "Public",
  "dct_format_s": "JPEG",
  "dct_references_s": "{\"http://schema.org/url\":\"https://digital.libraries.psu.edu/digital/collection/maps1/id/21929\",\"http://iiif.io/api/presentation#manifest\":\"https://digital.libraries.psu.edu/iiif/info/maps1/21929/manifest.json\"}",
  "id": "aa70edf3-c190-4932-b470-1ac33496e965",
  "dct_identifier_sm": [
    "aa70edf3-c190-4932-b470-1ac33496e965"
  ],
  "gbl_mdVersion_s": "Aardvark"
}