{
  "geoblacklight_version": "1.0",
  "dc_identifier_s": "3042cc89-136e-4e35-9848-6b9bc8d48f27",
  "dc_rights_s": "Public",
  "dc_title_s": "Brackenridge, Pennsylvania, 1929",
  "dct_provenance_s": "Pennsylvania State University",
  "layer_slug_s": "3042cc89-136e-4e35-9848-6b9bc8d48f27",
  "solr_geom": "ENVELOPE(-79.7508,-79.7331,40.6156,40.6007)",
  "solr_year_i": "1929",
  "dc_creator_sm": [
    "Sanborn Map Company"
  ],
  "dc_description_s": "Brackenridge, Allegheny County, Pennsylvania, November 1929. 1 map on 9 sheets : color ; sheets 65 x 54 cm.  Scale approximately 1:600. 50 ft. to an in. unless otherwise noted on individual sheets.",
  "dc_format_s": "JPEG",
  "dct_references_s": "{\"http://schema.org/url\":\"https://collection1.libraries.psu.edu/cdm/ref/collection/maps1/id/26258\",\"http://iiif.io/api/presentation#manifest\":\"https://digital.libraries.psu.edu/iiif/info/maps1/26258/manifest.json\"}",
  "dct_spatial_sm": [
    "Pennsylvania--Brackenridge",
    "Pennsylvania--Allegheny County",
    "Pennsylvania"
  ],
  "layer_modified_dt": "2023-04-14T01:01:08Z",
  "dc_language_sm": [
    "eng"
  ],
  "dc_publisher_s": "Sanborn Map Company",
  "dct_temporal_sm": [
    "1929"
  ]
}