{
  "geoblacklight_version": "1.0",
  "dc_identifier_s": "6616869e-55dd-4e1a-b5f4-1da67da7e827",
  "dc_rights_s": "Public",
  "dc_title_s": "State College, Pennsylvania, 1922",
  "dct_provenance_s": "Pennsylvania State University",
  "layer_slug_s": "6616869e-55dd-4e1a-b5f4-1da67da7e827",
  "solr_geom": "ENVELOPE(-77.886,-77.8192,40.8075,40.7685)",
  "solr_year_i": "1922",
  "dc_creator_sm": [
    "Sanborn Map Company"
  ],
  "dc_description_s": "State College, Centre County, Pennsylvania : June 1922. 15 sheets.  Scale not noted.",
  "dc_format_s": "JPEG",
  "dct_references_s": "{\"http://schema.org/url\":\"https://collection1.libraries.psu.edu/cdm/ref/collection/maps1/id/1014\",\"http://iiif.io/api/presentation#manifest\":\"https://digital.libraries.psu.edu/iiif/info/maps1/1014/manifest.json\"}",
  "dct_spatial_sm": [
    "Pennsylvania--State College",
    "Pennsylvania--Centre County",
    "Pennsylvania"
  ],
  "layer_modified_dt": "2023-04-14T01:00:44Z",
  "dc_language_sm": [
    "eng"
  ],
  "dc_publisher_s": "Sanborn Map Company",
  "dct_temporal_sm": [
    "1922"
  ]
}