{
  "geoblacklight_version": "1.0",
  "dc_identifier_s": "7cc0fc30-6391-4473-b697-23542c4d01ec",
  "dc_rights_s": "Public",
  "dc_title_s": "West Alexander, Pennsylvania, 1907",
  "dct_provenance_s": "Pennsylvania State University",
  "layer_slug_s": "7cc0fc30-6391-4473-b697-23542c4d01ec",
  "solr_geom": "ENVELOPE(-80.5143,-80.5012,40.1073,40.1009)",
  "solr_year_i": "1907",
  "dc_creator_sm": [
    "Sanborn Map Company"
  ],
  "dc_description_s": "West Alexander, Washington Co., Pa., December 1907. 1 map on 3 sheets : col. ; sheets 65 x 54 cm.  Scale approximately 1:600. 50 ft. to an in.",
  "dc_format_s": "JPEG",
  "dct_references_s": "{\"http://schema.org/url\":\"https://collection1.libraries.psu.edu/cdm/ref/collection/maps1/id/25169\",\"http://iiif.io/api/presentation#manifest\":\"https://digital.libraries.psu.edu/iiif/info/maps1/25169/manifest.json\"}",
  "dct_spatial_sm": [
    "West Alexander, Pennsylvania",
    "Washington County, Pennsylvania",
    "Pennsylvania"
  ],
  "layer_modified_dt": "2022-04-01T15:25:28Z",
  "dc_language_sm": [
    "eng"
  ],
  "dc_publisher_s": "Sanborn Map Company",
  "dct_temporal_sm": [
    "1907"
  ]
}